README.md
setup.py
hydrocarbon/__init__.py
hydrocarbon/app.py
hydrocarbon/core.py
hydrocarbon.egg-info/PKG-INFO
hydrocarbon.egg-info/SOURCES.txt
hydrocarbon.egg-info/dependency_links.txt
hydrocarbon.egg-info/entry_points.txt
hydrocarbon.egg-info/requires.txt
hydrocarbon.egg-info/top_level.txt