Metadata-Version: 2.1
Name: hydrocarbon
Version: 0.0.4
Summary: Generate a Carbon Black alliance feed in JSON format from a git repository
Home-page: https://github.com/edeca/hydrocarbon
Author: David Cannings
Author-email: david@edeca.net
License: Apache Software License
Platform: UNKNOWN
Classifier: Programming Language :: Python :: 3
Classifier: License :: OSI Approved :: Apache Software License
Classifier: Operating System :: OS Independent
Classifier: Development Status :: 4 - Beta
